setup.cfg
setup.py
rinocloud/__init__.py
rinocloud/batch.py
rinocloud/collection.py
rinocloud/config.py
rinocloud/http.py
rinocloud/object.py
rinocloud/query.py
rinocloud.egg-info/PKG-INFO
rinocloud.egg-info/SOURCES.txt
rinocloud.egg-info/dependency_links.txt
rinocloud.egg-info/requires.txt
rinocloud.egg-info/top_level.txt